{
	"textures": [
		{
			"image": "object_atlas.png",
			"format": "RGBA8888",
			"size": {
				"w": 552,
				"h": 494
			},
			"scale": 1,
			"frames": [
				{
					"filename": "control_sign",
					"rotated": false,
					"trimmed": false,
					"sourceSize": {
						"w": 314,
						"h": 224
					},
					"spriteSourceSize": {
						"x": 0,
						"y": 0,
						"w": 314,
						"h": 224
					},
					"frame": {
						"x": 1,
						"y": 1,
						"w": 314,
						"h": 224
					}
				},
				{
					"filename": "tree",
					"rotated": false,
					"trimmed": false,
					"sourceSize": {
						"w": 180,
						"h": 248
					},
					"spriteSourceSize": {
						"x": 0,
						"y": 0,
						"w": 180,
						"h": 248
					},
					"frame": {
						"x": 1,
						"y": 227,
						"w": 180,
						"h": 248
					}
				},
				{
					"filename": "floor",
					"rotated": false,
					"trimmed": false,
					"sourceSize": {
						"w": 132,
						"h": 132
					},
					"spriteSourceSize": {
						"x": 0,
						"y": 0,
						"w": 132,
						"h": 132
					},
					"frame": {
						"x": 317,
						"y": 1,
						"w": 132,
						"h": 132
					}
				},
				{
					"filename": "sun",
					"rotated": false,
					"trimmed": false,
					"sourceSize": {
						"w": 128,
						"h": 128
					},
					"spriteSourceSize": {
						"x": 0,
						"y": 0,
						"w": 128,
						"h": 128
					},
					"frame": {
						"x": 183,
						"y": 227,
						"w": 128,
						"h": 128
					}
				},
				{
					"filename": "teddy",
					"rotated": false,
					"trimmed": true,
					"sourceSize": {
						"w": 79,
						"h": 127
					},
					"spriteSourceSize": {
						"x": 1,
						"y": 0,
						"w": 76,
						"h": 127
					},
					"frame": {
						"x": 451,
						"y": 1,
						"w": 76,
						"h": 127
					}
				},
				{
					"filename": "walter",
					"rotated": false,
					"trimmed": true,
					"sourceSize": {
						"w": 63,
						"h": 110
					},
					"spriteSourceSize": {
						"x": 0,
						"y": 0,
						"w": 62,
						"h": 110
					},
					"frame": {
						"x": 183,
						"y": 357,
						"w": 62,
						"h": 110
					}
				},
				{
					"filename": "player/cleanwalk/walk0",
					"rotated": false,
					"trimmed": true,
					"sourceSize": {
						"w": 104,
						"h": 156
					},
					"spriteSourceSize": {
						"x": 22,
						"y": 6,
						"w": 60,
						"h": 150
					},
					"frame": {
						"x": 317,
						"y": 135,
						"w": 60,
						"h": 150
					}
				},
				{
					"filename": "player/cleanwalk/walk2",
					"rotated": false,
					"trimmed": true,
					"sourceSize": {
						"w": 104,
						"h": 156
					},
					"spriteSourceSize": {
						"x": 22,
						"y": 6,
						"w": 60,
						"h": 150
					},
					"frame": {
						"x": 317,
						"y": 135,
						"w": 60,
						"h": 150
					}
				},
				{
					"filename": "player/cleanwalk/walk3",
					"rotated": false,
					"trimmed": true,
					"sourceSize": {
						"w": 104,
						"h": 156
					},
					"spriteSourceSize": {
						"x": 20,
						"y": 6,
						"w": 60,
						"h": 150
					},
					"frame": {
						"x": 379,
						"y": 135,
						"w": 60,
						"h": 150
					}
				},
				{
					"filename": "corrine",
					"rotated": false,
					"trimmed": false,
					"sourceSize": {
						"w": 53,
						"h": 167
					},
					"spriteSourceSize": {
						"x": 0,
						"y": 0,
						"w": 53,
						"h": 167
					},
					"frame": {
						"x": 441,
						"y": 135,
						"w": 53,
						"h": 167
					}
				},
				{
					"filename": "player/cleanwalk/walk1",
					"rotated": false,
					"trimmed": true,
					"sourceSize": {
						"w": 104,
						"h": 156
					},
					"spriteSourceSize": {
						"x": 23,
						"y": 6,
						"w": 55,
						"h": 150
					},
					"frame": {
						"x": 496,
						"y": 130,
						"w": 55,
						"h": 150
					}
				},
				{
					"filename": "player/dirtywalk/walk1",
					"rotated": false,
					"trimmed": true,
					"sourceSize": {
						"w": 104,
						"h": 156
					},
					"spriteSourceSize": {
						"x": 23,
						"y": 6,
						"w": 55,
						"h": 150
					},
					"frame": {
						"x": 496,
						"y": 282,
						"w": 55,
						"h": 150
					}
				},
				{
					"filename": "carrot",
					"rotated": false,
					"trimmed": true,
					"sourceSize": {
						"w": 91,
						"h": 50
					},
					"spriteSourceSize": {
						"x": 2,
						"y": 2,
						"w": 88,
						"h": 48
					},
					"frame": {
						"x": 313,
						"y": 287,
						"w": 88,
						"h": 48
					}
				},
				{
					"filename": "grave",
					"rotated": false,
					"trimmed": false,
					"sourceSize": {
						"w": 57,
						"h": 74
					},
					"spriteSourceSize": {
						"x": 0,
						"y": 0,
						"w": 57,
						"h": 74
					},
					"frame": {
						"x": 247,
						"y": 357,
						"w": 57,
						"h": 74
					}
				},
				{
					"filename": "baby_carrots",
					"rotated": false,
					"trimmed": false,
					"sourceSize": {
						"w": 86,
						"h": 16
					},
					"spriteSourceSize": {
						"x": 0,
						"y": 0,
						"w": 86,
						"h": 16
					},
					"frame": {
						"x": 1,
						"y": 477,
						"w": 86,
						"h": 16
					}
				},
				{
					"filename": "carrot_item",
					"rotated": false,
					"trimmed": false,
					"sourceSize": {
						"w": 36,
						"h": 48
					},
					"spriteSourceSize": {
						"x": 0,
						"y": 0,
						"w": 36,
						"h": 48
					},
					"frame": {
						"x": 403,
						"y": 287,
						"w": 36,
						"h": 48
					}
				},
				{
					"filename": "tomato",
					"rotated": false,
					"trimmed": true,
					"sourceSize": {
						"w": 70,
						"h": 59
					},
					"spriteSourceSize": {
						"x": 2,
						"y": 2,
						"w": 65,
						"h": 57
					},
					"frame": {
						"x": 247,
						"y": 433,
						"w": 65,
						"h": 57
					}
				},
				{
					"filename": "player/dirtywalk/walk0",
					"rotated": false,
					"trimmed": true,
					"sourceSize": {
						"w": 104,
						"h": 156
					},
					"spriteSourceSize": {
						"x": 22,
						"y": 6,
						"w": 60,
						"h": 150
					},
					"frame": {
						"x": 314,
						"y": 337,
						"w": 60,
						"h": 150
					}
				},
				{
					"filename": "player/dirtywalk/walk2",
					"rotated": false,
					"trimmed": true,
					"sourceSize": {
						"w": 104,
						"h": 156
					},
					"spriteSourceSize": {
						"x": 22,
						"y": 6,
						"w": 60,
						"h": 150
					},
					"frame": {
						"x": 314,
						"y": 337,
						"w": 60,
						"h": 150
					}
				},
				{
					"filename": "player/dirtywalk/walk3",
					"rotated": false,
					"trimmed": true,
					"sourceSize": {
						"w": 104,
						"h": 156
					},
					"spriteSourceSize": {
						"x": 20,
						"y": 6,
						"w": 60,
						"h": 150
					},
					"frame": {
						"x": 376,
						"y": 337,
						"w": 60,
						"h": 150
					}
				},
				{
					"filename": "watermelon",
					"rotated": false,
					"trimmed": false,
					"sourceSize": {
						"w": 56,
						"h": 68
					},
					"spriteSourceSize": {
						"x": 0,
						"y": 0,
						"w": 56,
						"h": 68
					},
					"frame": {
						"x": 438,
						"y": 337,
						"w": 56,
						"h": 68
					}
				},
				{
					"filename": "overalls",
					"rotated": false,
					"trimmed": false,
					"sourceSize": {
						"w": 41,
						"h": 41
					},
					"spriteSourceSize": {
						"x": 0,
						"y": 0,
						"w": 41,
						"h": 41
					},
					"frame": {
						"x": 438,
						"y": 407,
						"w": 41,
						"h": 41
					}
				}
			]
		}
	],
	"meta": {
		"app": "https://www.codeandweb.com/texturepacker",
		"version": "3.0",
		"smartupdate": "$TexturePacker:SmartUpdate:620c3244a422aac348e3f99595460773:b9f58f35b594a0df4597a55c8e06a5eb:358f055dcd7752a1b7d514c352666090$"
	}
}